apc/Model.py
apc/__init__.py
apc/bartlett_test.py
apc/cl_bootstrap.py
apc/f_test.py
apc/r_test.py
apc/data/Belgian_lung_cancer.xlsx
apc/data/__init__.py
apc/data/asbestos_mortality.xlsx
apc/data/loss_BZ.csv
apc/data/loss_KN.csv
apc/data/loss_TA.csv
apc/data/loss_VNJ.xlsx
apc/data/pre_formatted.py
apc/tests/__init__.py
apc/tests/test_bartlett_test.py
apc/tests/test_bootstrap_forecast.py
apc/tests/test_clone.py
apc/tests/test_data_from_df.py
apc/tests/test_f_test.py
apc/tests/test_fit.py
apc/tests/test_fit_table.py
apc/tests/test_forecast.py
apc/tests/test_identify.py
apc/tests/test_plot_data_heatmaps.py
apc/tests/test_plot_data_sums.py
apc/tests/test_plot_data_within.py
apc/tests/test_plot_forecast.py
apc/tests/test_plot_parameters.py
apc/tests/test_plot_residuals.py
apc/tests/test_r_test.py
apc/tests/test_simulate.py
apc/vignettes/__init__.py
apc/vignettes/vignette_deviance_analysis.ipynb
apc/vignettes/vignette_generalized_log_normal.ipynb
apc/vignettes/vignette_ln_vs_odp.ipynb
apc/vignettes/vignette_mesothelioma.ipynb
apc/vignettes/vignette_misspecification.ipynb
apc/vignettes/vignette_over_dispersed_apc.ipynb
apc-1.0.2.dist-info/LICENSE.txt
apc-1.0.2.dist-info/METADATA
apc-1.0.2.dist-info/WHEEL
apc-1.0.2.dist-info/top_level.txt
apc-1.0.2.dist-info/RECORD
