Metadata-Version: 2.1
Name: apc
Version: 1.0.2
Summary: Age-Period-Cohort and extended Chain-Ladder Analysis
Home-page: http://github.com/JonasHarnau/apc
Author: Jonas Harnau
Author-email: j.harnau@outlook.com
License: GPLv3
Platform: UNKNOWN
Classifier: Development Status :: 3 - Alpha
Requires-Python: >=3.6
Requires-Dist: matplotlib
Requires-Dist: numpy
Requires-Dist: pandas (>=0.24.0)
Requires-Dist: quad-form-ratio
Requires-Dist: seaborn
Requires-Dist: scipy
Requires-Dist: statsmodels
